{"@context":"https://iiif.io/api/presentation/3/context.json","id":"https://basiakapolka.github.io/bookish-tribble/api/facet/publisher/southern-railway.json","type":"Collection","label":{"none":["Southern Railway"]},"items":[{"id":"https://api.dc.library.northwestern.edu/api/v2/works/929cc9a5-954d-4a18-842c-16f1597a2b4b?as=iiif","type":"Manifest","label":{"none":["Southern Railway (U.S.) Menu, Buffet service, 1962"]},"thumbnail":[{"id":"https://api.dc.library.northwestern.edu/api/v2/works/929cc9a5-954d-4a18-842c-16f1597a2b4b/thumbnail","type":"Image","format":"image/jpeg","height":300,"width":300}],"homepage":[{"id":"https://basiakapolka.github.io/bookish-tribble/works/southern-railway-us-menu-buffet-service-1962","type":"Text","label":{"none":["Southern Railway (U.S.) Menu, Buffet service, 1962"]}}]}],"partOf":[{"id":"https://basiakapolka.github.io/bookish-tribble/api/facet/publisher.json","type":"Collection"}],"summary":{"none":["Publisher"]},"homepage":[{"id":"https://basiakapolka.github.io/bookish-tribble/search?publisher=southern-railway","type":"Text","label":{"none":["Southern Railway"]}}]}